bathini/__init__.py
bathini/greet.py
bathini-0.1.4.dist-info/LICENSE
bathini-0.1.4.dist-info/METADATA
bathini-0.1.4.dist-info/WHEEL
bathini-0.1.4.dist-info/top_level.txt
bathini-0.1.4.dist-info/RECORD
